limecore/core/configuration/__init__.py
limecore/core/configuration/configuration.py
limecore/core/configuration/configuration_loader.py
limecore/core/configuration/module.py
limecore_core_configuration-0.2.1.dist-info/LICENSE.txt
limecore_core_configuration-0.2.1.dist-info/METADATA
limecore_core_configuration-0.2.1.dist-info/WHEEL
limecore_core_configuration-0.2.1.dist-info/top_level.txt
limecore_core_configuration-0.2.1.dist-info/RECORD
